{"frames": {

"begin":
{
	"frame": {"x":508,"y":370,"w":165,"h":77},
	"offset": {"x":0,"y":0,"w":165,"h":77},
	"sourceSize": {"w":165,"h":77}
},
"choose":
{
	"frame": {"x":212,"y":370,"w":136,"h":67},
	"offset": {"x":0,"y":0,"w":136,"h":67},
	"sourceSize": {"w":136,"h":67}
},
"general_bottom":
{
	"frame": {"x":673,"y":370,"w":166,"h":189},
	"offset": {"x":0,"y":0,"w":166,"h":189},
	"sourceSize": {"w":166,"h":189}
},
"general_content":
{
	"frame": {"x":606,"y":559,"w":234,"h":448},
	"offset": {"x":0,"y":0,"w":234,"h":448},
	"sourceSize": {"w":234,"h":448}
},
"general_content_left":
{
	"frame": {"x":292,"y":0,"w":44,"h":44},
	"offset": {"x":0,"y":0,"w":44,"h":44},
	"sourceSize": {"w":44,"h":44}
},
"general_content_middle":
{
	"frame": {"x":0,"y":0,"w":39,"h":47},
	"offset": {"x":0,"y":0,"w":39,"h":47},
	"sourceSize": {"w":39,"h":47}
},
"general_content_right":
{
	"frame": {"x":120,"y":0,"w":42,"h":48},
	"offset": {"x":0,"y":0,"w":42,"h":48},
	"sourceSize": {"w":42,"h":48}
},
"general_down":
{
	"frame": {"x":501,"y":0,"w":55,"h":370},
	"offset": {"x":0,"y":0,"w":55,"h":370},
	"sourceSize": {"w":55,"h":370}
},
"general_left":
{
	"frame": {"x":843,"y":0,"w":77,"h":212},
	"offset": {"x":0,"y":0,"w":77,"h":212},
	"sourceSize": {"w":77,"h":212}
},
"general_right":
{
	"frame": {"x":766,"y":0,"w":77,"h":212},
	"offset": {"x":0,"y":0,"w":77,"h":212},
	"sourceSize": {"w":77,"h":212}
},
"general_title":
{
	"frame": {"x":333,"y":1007,"w":338,"h":45},
	"offset": {"x":0,"y":0,"w":338,"h":45},
	"sourceSize": {"w":338,"h":45}
},
"general_top":
{
	"frame": {"x":186,"y":559,"w":189,"h":164},
	"offset": {"x":0,"y":0,"w":189,"h":164},
	"sourceSize": {"w":189,"h":164}
},
"general_up":
{
	"frame": {"x":336,"y":0,"w":55,"h":370},
	"offset": {"x":0,"y":0,"w":55,"h":370},
	"sourceSize": {"w":55,"h":370}
},
"image_back":
{
	"frame": {"x":106,"y":370,"w":106,"h":110},
	"offset": {"x":0,"y":0,"w":106,"h":110},
	"sourceSize": {"w":106,"h":110}
},
"lock":
{
	"frame": {"x":248,"y":0,"w":44,"h":66},
	"offset": {"x":0,"y":0,"w":44,"h":66},
	"sourceSize": {"w":44,"h":66}
},
"mark":
{
	"frame": {"x":205,"y":0,"w":43,"h":37},
	"offset": {"x":0,"y":0,"w":43,"h":37},
	"sourceSize": {"w":43,"h":37}
},
"question_mark":
{
	"frame": {"x":0,"y":370,"w":106,"h":110},
	"offset": {"x":0,"y":0,"w":106,"h":110},
	"sourceSize": {"w":106,"h":110}
},
"vip_back":
{
	"frame": {"x":0,"y":1052,"w":681,"h":551},
	"offset": {"x":0,"y":0,"w":681,"h":551},
	"sourceSize": {"w":681,"h":551}
},
"vip_bottom":
{
	"frame": {"x":348,"y":370,"w":160,"h":189},
	"offset": {"x":0,"y":0,"w":160,"h":189},
	"sourceSize": {"w":160,"h":189}
},
"vip_content":
{
	"frame": {"x":375,"y":559,"w":231,"h":448},
	"offset": {"x":0,"y":0,"w":231,"h":448},
	"sourceSize": {"w":231,"h":448}
},
"vip_content_left":
{
	"frame": {"x":162,"y":0,"w":43,"h":44},
	"offset": {"x":0,"y":0,"w":43,"h":44},
	"sourceSize": {"w":43,"h":44}
},
"vip_content_middle":
{
	"frame": {"x":39,"y":0,"w":39,"h":45},
	"offset": {"x":0,"y":0,"w":39,"h":45},
	"sourceSize": {"w":39,"h":45}
},
"vip_content_right":
{
	"frame": {"x":78,"y":0,"w":42,"h":42},
	"offset": {"x":0,"y":0,"w":42,"h":42},
	"sourceSize": {"w":42,"h":42}
},
"vip_down":
{
	"frame": {"x":391,"y":0,"w":55,"h":362},
	"offset": {"x":0,"y":0,"w":55,"h":362},
	"sourceSize": {"w":55,"h":362}
},
"vip_icon":
{
	"frame": {"x":556,"y":0,"w":66,"h":70},
	"offset": {"x":0,"y":0,"w":66,"h":70},
	"sourceSize": {"w":66,"h":70}
},
"vip_left":
{
	"frame": {"x":694,"y":0,"w":72,"h":212},
	"offset": {"x":0,"y":0,"w":72,"h":212},
	"sourceSize": {"w":72,"h":212}
},
"vip_right":
{
	"frame": {"x":622,"y":0,"w":72,"h":212},
	"offset": {"x":0,"y":0,"w":72,"h":212},
	"sourceSize": {"w":72,"h":212}
},
"vip_title":
{
	"frame": {"x":0,"y":1007,"w":333,"h":45},
	"offset": {"x":0,"y":0,"w":333,"h":45},
	"sourceSize": {"w":333,"h":45}
},
"vip_top":
{
	"frame": {"x":0,"y":559,"w":186,"h":164},
	"offset": {"x":0,"y":0,"w":186,"h":164},
	"sourceSize": {"w":186,"h":164}
},
"vip_up":
{
	"frame": {"x":446,"y":0,"w":55,"h":362},
	"offset": {"x":0,"y":0,"w":55,"h":362},
	"sourceSize": {"w":55,"h":362}
}},
"meta": {
	"app": "https://www.codeandweb.com/texturepacker",
	"version": "1.0",
	"image": "blockcity_tiger_lottery.png",
	"format": "RGBA8888",
	"size": {"w":1024,"h":2048},
	"scale": "1"
}
}
