{
"ResConfig": {
"Font": [
  {
"Type": "FreeType",
"Name": "HT8",
"Filename": "DroidSans.ttf",
"Language": "zh_CN,en_US,zh_TW,tr_TR,vi_VN,it_IT,in_ID,fr_FR,es_ES,de_DE,pt_BR,ru_RU,th_TH,ko_KR",
"Size": 8
},
  {
"Type": "FreeType",
"Name": "HT10",
"Filename": "DroidSans.ttf",
"Language": "zh_CN,en_US,zh_TW,tr_TR,vi_VN,it_IT,in_ID,fr_FR,es_ES,de_DE,pt_BR,ru_RU,th_TH,ko_KR",
"Size": 10
},
  {
"Type": "FreeType",
"Name": "HT12",
"Filename": "DroidSans.ttf",
"Language": "zh_CN,en_US,zh_TW,tr_TR,vi_VN,it_IT,in_ID,fr_FR,es_ES,de_DE,pt_BR,ru_RU,th_TH,ko_KR",
"Size": 12
},
{
"Type": "FreeType",
"Name": "HT14",
"Filename": "DroidSans.ttf",
"Language": "zh_CN,en_US,zh_TW,tr_TR,vi_VN,it_IT,in_ID,fr_FR,es_ES,de_DE,pt_BR,ru_RU,th_TH,ko_KR",
"Size": 14
},
{
"Type": "FreeType",
"Name": "HT16",
"Filename": "DroidSans.ttf",
	"Language": "zh_CN,en_US,zh_TW,tr_TR,vi_VN,it_IT,in_ID,fr_FR,es_ES,de_DE,pt_BR,ru_RU,th_TH,ko_KR",
"Size": 16
  },
  {
"Type": "FreeType",
"Name": "HT18",
"Filename": "DroidSans.ttf",
"Language": "zh_CN,en_US,zh_TW,tr_TR,vi_VN,it_IT,in_ID,fr_FR,es_ES,de_DE,pt_BR,ru_RU,th_TH,ko_KR",
"Size": 18
},
{
"Type": "FreeType",
"Name": "HT20",
"Filename": "DroidSans.ttf",
	"Language": "zh_CN,en_US,zh_TW,tr_TR,vi_VN,it_IT,in_ID,fr_FR,es_ES,de_DE,pt_BR,ru_RU,th_TH,ko_KR",
"Size": 20
  },
  {
"Type": "FreeType",
"Name": "HT22",
"Filename": "DroidSans.ttf",
"Language": "zh_CN,en_US,zh_TW,tr_TR,vi_VN,it_IT,in_ID,fr_FR,es_ES,de_DE,pt_BR,ru_RU,th_TH,ko_KR",
"Size": 22
},
{
"Type": "FreeType",
"Name": "HT24",
"Filename": "DroidSans.ttf",
	"Language": "zh_CN,en_US,zh_TW,tr_TR,vi_VN,it_IT,in_ID,fr_FR,es_ES,de_DE,pt_BR,ru_RU,th_TH,ko_KR",
"Size": 24
      },
      {
        "Type": "FreeType",
        "Name": "HT26",
        "Filename": "DroidSans.ttf",
        "Language": "zh_CN,en_US,zh_TW,tr_TR,vi_VN,it_IT,in_ID,fr_FR,es_ES,de_DE,pt_BR,ru_RU,th_TH,ko_KR",
        "Size": 26
      },
      {
        "Type": "FreeType",
        "Name": "HT28",
        "Filename": "DroidSans.ttf",
        "Language": "zh_CN,en_US,zh_TW,tr_TR,vi_VN,it_IT,in_ID,fr_FR,es_ES,de_DE,pt_BR,ru_RU,th_TH,ko_KR",
        "Size": 28
      },
	  {
        "Type": "FreeType",
        "Name": "HT30",
        "Filename": "DroidSans.ttf",
        "Language": "zh_CN,en_US,zh_TW,tr_TR,vi_VN,it_IT,in_ID,fr_FR,es_ES,de_DE,pt_BR,ru_RU,th_TH,ko_KR",
        "Size": 30
      },
	  {
        "Type": "FreeType",
        "Name": "HT32",
        "Filename": "DroidSans.ttf",
        "Language": "zh_CN,en_US,zh_TW,tr_TR,vi_VN,it_IT,in_ID,fr_FR,es_ES,de_DE,pt_BR,ru_RU,th_TH,ko_KR",
        "Size": 32
      },
	  {
        "Type": "FreeType",
        "Name": "HT34",
        "Filename": "DroidSans.ttf",
        "Language": "zh_CN,en_US,zh_TW,tr_TR,vi_VN,it_IT,in_ID,fr_FR,es_ES,de_DE,pt_BR,ru_RU,th_TH,ko_KR",
        "Size": 34
      },
	  {
        "Type": "FreeType",
        "Name": "HT36",
        "Filename": "DroidSans.ttf",
        "Language": "zh_CN,en_US,zh_TW,tr_TR,vi_VN,it_IT,in_ID,fr_FR,es_ES,de_DE,pt_BR,ru_RU,th_TH,ko_KR",
        "Size": 36
      },
	  {
        "Type": "FreeType",
        "Name": "HT48",
        "Filename": "DroidSans.ttf",
        "Language": "zh_CN,en_US,zh_TW,tr_TR,vi_VN,it_IT,in_ID,fr_FR,es_ES,de_DE,pt_BR,ru_RU,th_TH,ko_KR",
        "Size": 48
      },
	  {
        "Type": "FreeType",
        "Name": "HT64",
        "Filename": "DroidSans.ttf",
        "Language": "zh_CN,en_US,zh_TW,tr_TR,vi_VN,it_IT,in_ID,fr_FR,es_ES,de_DE,pt_BR,ru_RU,th_TH,ko_KR",
        "Size": 64
      },
	  {
        "Type": "FreeType",
        "Name": "HT72",
        "Filename": "DroidSans.ttf",
        "Language": "zh_CN,en_US,zh_TW,tr_TR,vi_VN,it_IT,in_ID,fr_FR,es_ES,de_DE,pt_BR,ru_RU,th_TH,ko_KR",
        "Size": 72
      },
	  {
        "Type": "FreeType",
        "Name": "HT120",
        "Filename": "DroidSans.ttf",
        "Language": "zh_CN,en_US,zh_TW,tr_TR,vi_VN,it_IT,in_ID,fr_FR,es_ES,de_DE,pt_BR,ru_RU,th_TH,ko_KR",
        "Size": 120
      },
	  {
        "Type": "FreeType",
        "Name": "HT160",
        "Filename": "DroidSans.ttf",
        "Language": "zh_CN,en_US,zh_TW,tr_TR,vi_VN,it_IT,in_ID,fr_FR,es_ES,de_DE,pt_BR,ru_RU,th_TH,ko_KR",
        "Size": 160
      }
    ],
    "Imageset": [
      { "Filename": "MainControlImageSet.json" },
      { "Filename": "inventory.json" },
      { "Filename": "widgets.json" },
      { "Filename": "compass_gui.json" },
      { "Filename": "clock_gui.json" },
      { "Filename": "creative_inventory.json" },
      { "Filename": "mask.json" },
      { "Filename": "Pack.json" },
      { "Filename": "background.json" },
      { "Filename": "christmas_ui.json" },
      { "Filename": "ender_ui.json" },
      { "Filename": "normal_ui.json" },
      { "Filename": "trapped_ui.json" },
      { "Filename": "gui_material.json" },
      { "Filename": "gui_inventory_icon.json" },
      { "Filename": "new_gui_material.json" },
      { "Filename": "player_info_icon.json" },
      { "Filename": "gui_shop.json" },
      { "Filename": "summary.json" },
      { "Filename": "wordart.json" },
      { "Filename": "wordart_zh_cn.json" },
      { "Filename": "gameloading.json" },
      { "Filename": "teamInfo.json" },
      { "Filename": "gun.json" },
      { "Filename": "main_btn.json" },
      { "Filename": "app_shop.json" },
      { "Filename": "other_icon.json" },
      { "Filename": "jail_break.json" },
      { "Filename": "shop_tab_icon.json" },
      { "Filename": "sandDigger.json" },
      { "Filename": "loadingBlock.json" },
      { "Filename": "chicken_icon.json" },
      { "Filename": "pole.json" },
      { "Filename": "hideandseek.json" },
      { "Filename": "manor_atlas.json" },
      { "Filename": "creepy_aliens.json" },
      { "Filename": "buildwar.json"},
      { "Filename": "shoot_warning.json" },
      { "Filename": "ending_status.json"},
      { "Filename": "keysetting.json" },
      { "Filename": "parachute_f.json" },
      { "Filename": "reload_bullet_r.json" },
      { "Filename": "aim_target.json" },
      { "Filename": "app_shop_keyboard.json" },
      { "Filename": "personal_shop_keyboard.json" },
      { "Filename": "change_actor_keyboard.json" },
      { "Filename": "change_camera_status_keyboard.json" },
      { "Filename": "car_progress.json" },
      { "Filename": "frozen_mask.json" },
      { "Filename": "shoot_warning.json" },
      { "Filename": "btn_fishing.json" },
      { "Filename": "btn_cannon.json" },
      { "Filename": "CarTeam.json" },
      { "Filename": "ranch_main.json" },
      { "Filename": "ranch_icon.json" },
      { "Filename": "ranch_build.json" },
      { "Filename": "ranch_rank.json" },
      { "Filename": "ranch_order.json" },
      { "Filename": "ranchersexplore.json" },
      { "Filename": "ranch_boy_icon.json" },
      { "Filename": "ranch_girl_icon.json" },
      { "Filename": "tycoon_unlock.json" },
      { "Filename": "enchantment.json" },
      { "Filename": "tiger_lottery.json" },
      { "Filename": "hideandseekhallbg.json" },
      { "Filename": "hidden.json" },
      { "Filename": "pixelgunhallmodeselect.json" },
      { "Filename": "pixelgunhallmodeselectbg.json" },
      { "Filename": "gun_store.json" },
      { "Filename": "pixelgun1v1.json" },
      { "Filename": "chest_lottery.json" },
      { "Filename": "pixelgunrevive.json" },
      { "Filename": "pixelgungameresult.json" },
      { "Filename": "tip_dialog.json" },
      { "Filename": "season_rank.json" },
      { "Filename": "armor.json" },
      { "Filename": "pixelgungamebig.json" },
      { "Filename": "bird_main.json" },
      { "Filename": "bird_pack.json" },
      { "Filename": "bird_personalShop.json" },
      { "Filename": "bird_task.json" },
      { "Filename": "bird_store.json" },
      { "Filename": "bird_atlas.json" },
      { "Filename": "bird_activity.json" },
      { "Filename": "bird_checkin.json" },
      { "Filename": "pixel_gun_task.json" },
      { "Filename": "btn_quickly_build_block.json" },
      { "Filename": "selectable_action_img.json" },
      { "Filename": "pixel_gun_ad.json" },
      { "Filename": "brief_introduction.json" },
      { "Filename": "guide.json" },
      { "Filename": "pixel_gun_sign_in.json" },
      { "Filename": "dress.json" },
      { "Filename": "rune.json" },
      { "Filename": "pixel_gun_indie_main.json" },
      { "Filename": "pixel_gun_gift_bag_store.json" },
      { "Filename": "advertice.json" },
      { "Filename": "blockcity_tiger_lottery.json" },
      { "Filename": "blockcity_manor.json" },
      { "Filename": "blockcity_store.json" },
      { "Filename": "blockcity_friend.json" },
      { "Filename": "blockcity_checkin.json.json" },
      { "Filename": "blockcity_rank.json" },
      { "Filename": "blockcity_main_tip.json" },
      { "Filename": "blockcity_choose_paper.json" },
      { "Filename": "common_tip.json" },
      { "Filename": "blockcity_buy_fly.json" },
      { "Filename": "pixelgun_kuang.json" },
      { "Filename": "drive.json" },
      { "Filename": "skyblock_main.json" },
      { "Filename": "skyblock_Island.json" },
      { "Filename": "skyblock_book.json" },
      { "Filename": "skyblockbag.json" },
      { "Filename": "skyblock_dialog.json" },
      { "Filename": "skyblock_task.json" },
      { "Filename": "skyblock_task_bg.json" },
      { "Filename": "skyblock_shop.json" },
      { "Filename": "skyblock_rank.json" },
      { "Filename": "skyblock_rank_bg.json" },
      { "Filename": "walkingdead_formulation.json" },
      { "Filename": "walkingdead_store.json" },
      { "Filename": "walkingdead_supply.json" },
      { "Filename": "walking_dead_designation.json" },
      { "Filename": "walkingdead_mainInventory.json" },
      { "Filename": "walkingdead_death_settlement.json" },
      { "Filename": "walkingdead_armor.json" },
      { "Filename": "walkingdead_block.json" },
      { "Filename": "walkingdead_three_dialog.json" },
      { "Filename": "notification.json" },
      { "Filename": "tycoon_ad.json" },
      { "Filename": "blockfort_main.json" },
      { "Filename": "blockfort_manor_upgrade.json" },
      { "Filename": "blockfort_store.json" },
      { "Filename": "blockfort_friend.json" },
      { "Filename": "blockfort_building.json" },
      { "Filename": "blockfort_common.json" },
      { "Filename": "blockfort_pack.json" },
      { "Filename": "blockfort_player_operation.json" },
      { "Filename": "blockcity_main_ui.json" },
      { "Filename": "blockcity_house_shop.json" },
      { "Filename": "blockcity_pack.json" },
      { "Filename": "blockcity_elevator.json" },
      { "Filename": "blockcity_get_flower.json" },
      { "Filename": "blockcity_charm_rank.json" },
      { "Filename": "blockcity_rank_award.json" },
      { "Filename": "user_item.json" },
      { "Filename": "pixel_chicken_main.json" },
      { "Filename": "new_money.json" },
      { "Filename": "item_duration_progress.json" },
      { "Filename": "blockcity_save_file.json" },
      { "Filename": "blockcity_ad.json" },
      { "Filename": "bird_ad.json" },
      { "Filename": "blockcity_portal.json" },
      { "Filename": "blockcity_race_vehicle.json" },
      { "Filename": "skyblock_privilege_shop.json" },
      { "Filename": "skyblock_sign_in.json" },
      { "Filename": "bed_war_lottery.json" },
      { "Filename": "walkingDeadMiniMap.json" },
      { "Filename": "bullet_reload.json" },
      { "Filename": "lucky_sky_chest_inv.json" },
      { "Filename": "lucky_sky_backpack.json" },
      { "Filename": "camera_distance.json" },
      { "Filename": "fly_control.json" },
      { "Filename": "move_state.json" },
      { "Filename": "jump_control.json" },
      { "Filename": "arrow_key.json" }
    ]
  }
}
