{
    "Dialog": {
        "Window": {
            "Type": "Layout",
            "Name": "BirdCheckin",
            "Property": [
                {
                    "Name": "Area",
                    "Value": "{{0,0},{0,0},{1,0},{1,0}}"
                },
                {
                    "Name": "WndOpenSound",
                    "Value": "0"
                },
                {
                    "Name": "WndCloseSound",
                    "Value": "0"
                }
            ],
            "Window": [
                {
                    "Type": "Layout",
                    "Name": "BirdCheckin-Panel",
                    "Property": [
                        {
                            "Name": "Area",
                            "Value": "{{0,0},{0,-15},{0.685938,0},{1,-100}}"
                        },
                        {
                            "Name": "VerticalAlignment",
                            "Value": "Bottom"
                        },
                        {
                            "Name": "HorizontalAlignment",
                            "Value": "Centre"
                        },
                        {
                            "Name": "Touchable",
                            "Value": "false"
                        },
                        {
                            "Name": "WndOpenSound",
                            "Value": "0"
                        },
                        {
                            "Name": "WndCloseSound",
                            "Value": "0"
                        },
                        {
                            "Name": "StretchType",
                            "Value": "NineGrid"
                        },
                        {
                            "Name": "StretchOffset",
                            "Value": "20 20 67 87"
                        },
                        {
                            "Name": "LayoutBackImage",
                            "Value": "set:bird_checkin.json image:checkin_bg"
                        }
                    ],
                    "Window": [
                        {
                            "Type": "StaticImage",
                            "Name": "BirdCheckin-Panel-Figure",
                            "Property": [
                                {
                                    "Name": "Area",
                                    "Value": "{{0,0},{0,0},{0.968109,0},{0.489764,0}}"
                                },
                                {
                                    "Name": "VerticalAlignment",
                                    "Value": "Centre"
                                },
                                {
                                    "Name": "HorizontalAlignment",
                                    "Value": "Centre"
                                },
                                {
                                    "Name": "Touchable",
                                    "Value": "false"
                                },
                                {
                                    "Name": "WndOpenSound",
                                    "Value": "0"
                                },
                                {
                                    "Name": "WndCloseSound",
                                    "Value": "0"
                                },
                                {
                                    "Name": "ImageName",
                                    "Value": "set:bird_checkin.json image:checkin_bg_figure"
                                },
                                {
                                    "Name": "HexgonTopImage",
                                    "Value": ""
                                },
                                {
                                    "Name": "HexgonTopColor",
                                    "Value": "1 1 1 1"
                                },
                                {
                                    "Name": "HexgonSideImage",
                                    "Value": ""
                                },
                                {
                                    "Name": "HexgonSideColor",
                                    "Value": "1 1 1 1"
                                },
                                {
                                    "Name": "HexgonOverlayerImage",
                                    "Value": ""
                                },
                                {
                                    "Name": "HexgonOverlayerColor",
                                    "Value": "1 1 1 1"
                                }
                            ]
                        },
                        {
                            "Type": "Button",
                            "Name": "BirdCheckin-Close",
                            "Property": [
                                {
                                    "Name": "Area",
                                    "Value": "{{0,10},{0,-11.5},{0,95},{0,78.5}}"
                                },
                                {
                                    "Name": "HorizontalAlignment",
                                    "Value": "Right"
                                },
                                {
                                    "Name": "WndOpenSound",
                                    "Value": "0"
                                },
                                {
                                    "Name": "WndCloseSound",
                                    "Value": "0"
                                },
                                {
                                    "Name": "NormalImage",
                                    "Value": "set:bird_pack.json image:close"
                                },
                                {
                                    "Name": "PushedImage",
                                    "Value": "set:bird_pack.json image:close"
                                },
                                {
                                    "Name": "SoundName",
                                    "Value": "0"
                                },
                                {
                                    "Name": "HexgonTopImage",
                                    "Value": ""
                                },
                                {
                                    "Name": "HexgonTopColor",
                                    "Value": "1 1 1 1"
                                },
                                {
                                    "Name": "HexgonSideImage",
                                    "Value": ""
                                },
                                {
                                    "Name": "HexgonSideColor",
                                    "Value": "1 1 1 1"
                                },
                                {
                                    "Name": "HexgonOverlayerImage",
                                    "Value": ""
                                },
                                {
                                    "Name": "HexgonOverlayerColor",
                                    "Value": "1 1 1 1"
                                }
                            ]
                        },
                        {
                            "Type": "Button",
                            "Name": "BirdCheckin-Title",
                            "Property": [
                                {
                                    "Name": "Area",
                                    "Value": "{{0,0},{0,0},{0.654897,0},{0,66}}"
                                },
                                {
                                    "Name": "HorizontalAlignment",
                                    "Value": "Centre"
                                },
                                {
                                    "Name": "Text",
                                    "Value": "七日累计登录"
                                },
                                {
                                    "Name": "Font",
                                    "Value": "HT24"
                                },
                                {
                                    "Name": "Touchable",
                                    "Value": "false"
                                },
                                {
                                    "Name": "WndOpenSound",
                                    "Value": "0"
                                },
                                {
                                    "Name": "WndCloseSound",
                                    "Value": "0"
                                },
                                {
                                    "Name": "BtnTextColor",
                                    "Value": "1 0.917647 0.341176 1"
                                },
                                {
                                    "Name": "TextBorder",
                                    "Value": "true"
                                },
                                {
                                    "Name": "TextBorderColor",
                                    "Value": "0.505882 0.168627 0.168627 1"
                                },
                                {
                                    "Name": "NormalImage",
                                    "Value": "set:bird_checkin.json image:checkin_title"
                                },
                                {
                                    "Name": "PushedImage",
                                    "Value": "set:bird_checkin.json image:checkin_title"
                                },
                                {
                                    "Name": "SoundName",
                                    "Value": "0"
                                },
                                {
                                    "Name": "TextRenderOffset",
                                    "Value": "0 -4"
                                },
                                {
                                    "Name": "HexgonTopImage",
                                    "Value": ""
                                },
                                {
                                    "Name": "HexgonTopColor",
                                    "Value": "1 1 1 1"
                                },
                                {
                                    "Name": "HexgonSideImage",
                                    "Value": ""
                                },
                                {
                                    "Name": "HexgonSideColor",
                                    "Value": "1 1 1 1"
                                },
                                {
                                    "Name": "HexgonOverlayerImage",
                                    "Value": ""
                                },
                                {
                                    "Name": "HexgonOverlayerColor",
                                    "Value": "1 1 1 1"
                                }
                            ]
                        },
                        {
                            "Type": "GridView",
                            "Name": "BirdCheckin-Items",
                            "Property": [
                                {
                                    "Name": "Area",
                                    "Value": "{{0,0},{0,72},{1,-72},{1,-98}}"
                                },
                                {
                                    "Name": "HorizontalAlignment",
                                    "Value": "Centre"
                                },
                                {
                                    "Name": "Touchable",
                                    "Value": "false"
                                },
                                {
                                    "Name": "ClipChild",
                                    "Value": "true"
                                },
                                {
                                    "Name": "WndOpenSound",
                                    "Value": "0"
                                },
                                {
                                    "Name": "WndCloseSound",
                                    "Value": "0"
                                },
                                {
                                    "Name": "ItemAlignment",
                                    "Value": "Left"
                                }
                            ]
                        },
                        {
                            "Type": "StaticText",
                            "Name": "BirdCheckin-TimeLeft",
                            "Property": [
                                {
                                    "Name": "Area",
                                    "Value": "{{0,12},{0,-3},{0.734624,12},{0,81}}"
                                },
                                {
                                    "Name": "VerticalAlignment",
                                    "Value": "Bottom"
                                },
                                {
                                    "Name": "Text",
                                    "Value": "签到剩余时间：10:01:30"
                                },
                                {
                                    "Name": "Font",
                                    "Value": "HT20"
                                },
                                {
                                    "Name": "Touchable",
                                    "Value": "false"
                                },
                                {
                                    "Name": "WndOpenSound",
                                    "Value": "0"
                                },
                                {
                                    "Name": "WndCloseSound",
                                    "Value": "0"
                                },
                                {
                                    "Name": "TextHorzAlignment",
                                    "Value": "Centre"
                                },
                                {
                                    "Name": "TextVertAlignment",
                                    "Value": "Centre"
                                },
                                {
                                    "Name": "TextBorder",
                                    "Value": "true"
                                },
                                {
                                    "Name": "TextBorderColor",
                                    "Value": "0.482353 0.0117647 0.105882 1"
                                },
                                {
                                    "Name": "TextLineExtraSpace",
                                    "Value": "0"
                                }
                            ],
                            "Window": [
                                {
                                    "Type": "Button",
                                    "Name": "BirdCheckin-Checkin",
                                    "Property": [
                                        {
                                            "Name": "Area",
                                            "Value": "{{1,0},{0,0},{1.24961,0},{0,58}}"
                                        },
                                        {
                                            "Name": "VerticalAlignment",
                                            "Value": "Centre"
                                        },
                                        {
                                            "Name": "Text",
                                            "Value": "领取"
                                        },
                                        {
                                            "Name": "Font",
                                            "Value": "HT20"
                                        },
                                        {
                                            "Name": "WndOpenSound",
                                            "Value": "0"
                                        },
                                        {
                                            "Name": "WndCloseSound",
                                            "Value": "0"
                                        },
                                        {
                                            "Name": "TextBorder",
                                            "Value": "true"
                                        },
                                        {
                                            "Name": "TextBorderColor",
                                            "Value": "0.101961 0.298039 0.262745 1"
                                        },
                                        {
                                            "Name": "NormalImage",
                                            "Value": "set:bird_pack.json image:feedButton"
                                        },
                                        {
                                            "Name": "PushedImage",
                                            "Value": "set:bird_pack.json image:feedButton"
                                        },
                                        {
                                            "Name": "SoundName",
                                            "Value": "0"
                                        },
                                        {
                                            "Name": "TextRenderOffset",
                                            "Value": "0 -2"
                                        },
                                        {
                                            "Name": "HexgonTopImage",
                                            "Value": ""
                                        },
                                        {
                                            "Name": "HexgonTopColor",
                                            "Value": "1 1 1 1"
                                        },
                                        {
                                            "Name": "HexgonSideImage",
                                            "Value": ""
                                        },
                                        {
                                            "Name": "HexgonSideColor",
                                            "Value": "1 1 1 1"
                                        },
                                        {
                                            "Name": "HexgonOverlayerImage",
                                            "Value": ""
                                        },
                                        {
                                            "Name": "HexgonOverlayerColor",
                                            "Value": "1 1 1 1"
                                        }
                                    ]
                                }
                            ]
                        }
                    ]
                }
            ]
        }
    }
}